Classfile /D:/Projects/Github/code-samples/java/javase-samples/java8-samples/target/classes/sample/java/primary/oop/inner/AnonymousInnerClass$1.class
  Last modified 2022-4-17; size 709 bytes
  MD5 checksum 3e5951e3d86acb6a1ec144645f38d6fd
  Compiled from "AnonymousInnerClass.java"
class sample.java8.primary.oop.inner.AnonymousInnerClass$1 implements sample.java8.primary.oop.inner.I2
  minor version: 0
  major version: 52
  flags: ACC_SUPER
Constant pool:
   #1 = Class              #2             // sample/java/primary/oop/inner/AnonymousInnerClass$1
   #2 = Utf8               sample/java/primary/oop/inner/AnonymousInnerClass$1
   #3 = Class              #4             // java/lang/Object
   #4 = Utf8               java/lang/Object
   #5 = Class              #6             // sample/java/primary/oop/inner/I2
   #6 = Utf8               sample/java/primary/oop/inner/I2
   #7 = Utf8               this$0
   #8 = Utf8               Lsample/java/primary/oop/inner/AnonymousInnerClass;
   #9 = Utf8               <init>
  #10 = Utf8               (Lsample/java/primary/oop/inner/AnonymousInnerClass;)V
  #11 = Utf8               Code
  #12 = Fieldref           #1.#13         // sample/java/primary/oop/inner/AnonymousInnerClass$1.this$0:Lsample/java/primary/oop/inner/AnonymousInnerClass;
  #13 = NameAndType        #7:#8          // this$0:Lsample/java/primary/oop/inner/AnonymousInnerClass;
  #14 = Methodref          #3.#15         // java/lang/Object."<init>":()V
  #15 = NameAndType        #9:#16         // "<init>":()V
  #16 = Utf8               ()V
  #17 = Utf8               LineNumberTable
  #18 = Utf8               LocalVariableTable
  #19 = Utf8               this
  #20 = Utf8               Lsample/java/primary/oop/inner/AnonymousInnerClass$1;
  #21 = Utf8               method
  #22 = Utf8               SourceFile
  #23 = Utf8               AnonymousInnerClass.java
  #24 = Utf8               EnclosingMethod
  #25 = Class              #26            // sample/java/primary/oop/inner/AnonymousInnerClass
  #26 = Utf8               sample/java/primary/oop/inner/AnonymousInnerClass
  #27 = Utf8               InnerClasses
{
  final sample.java8.primary.oop.inner.AnonymousInnerClass this$0;
    descriptor: Lsample/java/primary/oop/inner/AnonymousInnerClass;
    flags: ACC_FINAL, ACC_SYNTHETIC

  sample.java8.primary.oop.inner.AnonymousInnerClass$1(sample.java8.primary.oop.inner.AnonymousInnerClass);
    descriptor: (Lsample/java/primary/oop/inner/AnonymousInnerClass;)V
    flags:
    Code:
      stack=2, locals=2, args_size=2
         0: aload_0
         1: aload_1
         2: putfield      #12                 // Field this$0:Lsample/java/primary/oop/inner/AnonymousInnerClass;
         5: aload_0
         6: invokespecial #14                 // Method java/lang/Object."<init>":()V
         9: return
      LineNumberTable:
        line 9: 0
      LocalVariableTable:
        Start  Length  Slot  Name   Signature
            0      10     0  this   Lsample/java/primary/oop/inner/AnonymousInnerClass$1;

  public void method();
    descriptor: ()V
    flags: ACC_PUBLIC
    Code:
      stack=0, locals=1, args_size=1
         0: return
      LineNumberTable:
        line 13: 0
      LocalVariableTable:
        Start  Length  Slot  Name   Signature
            0       1     0  this   Lsample/java/primary/oop/inner/AnonymousInnerClass$1;
}
SourceFile: "AnonymousInnerClass.java"
EnclosingMethod: #25.#0                 // sample.java8.primary.oop.inner.AnonymousInnerClass
InnerClasses:
     #1; //class sample/java/primary/oop/inner/AnonymousInnerClass$1
